src/libx/__init__.py
src/libx/web/__init__.py
src/libx/web/home.py
libx_alwaysprep-0.2.0.dist-info/LICENSE
libx_alwaysprep-0.2.0.dist-info/METADATA
libx_alwaysprep-0.2.0.dist-info/WHEEL
libx_alwaysprep-0.2.0.dist-info/top_level.txt
libx_alwaysprep-0.2.0.dist-info/RECORD
